{
  "Hosts": [
    {
      "Kind": "svt_infra_1",
      "Results": [
        {
          "Kind": "hyperkube_kubelet_",
          "Resource": "cpu_usage_percent_cpu",
          "Min": 1.5,
          "Max": 7.5,
          "Avg": 3.116260869565216,
          "Pct95": 6.2
        },
        {
          "Kind": "prometheus_",
          "Resource": "cpu_usage_percent_cpu",
          "Min": 10.5,
          "Max": 45,
          "Avg": 19.412434782608692,
          "Pct95": 31.619999999999997
        },
        {
          "Kind": "systemd_--switched-root",
          "Resource": "cpu_usage_percent_cpu",
          "Min": 0,
          "Max": 0.3,
          "Avg": 0.009565217391304347,
          "Pct95": 0.1
        },
        {
          "Kind": "ovs-vswitchd_unix",
          "Resource": "cpu_usage_percent_cpu",
          "Min": 0.2,
          "Max": 0.5,
          "Avg": 0.3104347826086955,
          "Pct95": 0.4
        },
        {
          "Kind": "crio",
          "Resource": "cpu_usage_percent_cpu",
          "Min": 0,
          "Max": 0,
          "Avg": 0,
          "Pct95": 0
        },
        {
          "Kind": "nvme0n1-write",
          "Resource": "disk_IOPS",
          "Min": 0,
          "Max": 45.9,
          "Avg": 9.817391304347826,
          "Pct95": 25.199999999999996
        },
        {
          "Kind": "nvme0n1-read",
          "Resource": "disk_IOPS",
          "Min": 0,
          "Max": 0,
          "Avg": 0,
          "Pct95": 0
        },
        {
          "Kind": "hyperkube_kubelet_",
          "Resource": "memory_usage_resident_set_size",
          "Min": 190936,
          "Max": 195564,
          "Avg": 193381.28695652174,
          "Pct95": 195564
        },
        {
          "Kind": "prometheus_",
          "Resource": "memory_usage_resident_set_size",
          "Min": 1289088,
          "Max": 1446644,
          "Avg": 1345867.5478260869,
          "Pct95": 1426927.2
        },
        {
          "Kind": "systemd_--switched-root",
          "Resource": "memory_usage_resident_set_size",
          "Min": 7464,
          "Max": 7464,
          "Avg": 7464,
          "Pct95": 7464
        },
        {
          "Kind": "ovs-vswitchd_unix",
          "Resource": "memory_usage_resident_set_size",
          "Min": 60004,
          "Max": 60004,
          "Avg": 60004,
          "Pct95": 60004
        },
        {
          "Kind": "crio",
          "Resource": "memory_usage_resident_set_size",
          "Min": 1040,
          "Max": 1040,
          "Avg": 1040,
          "Pct95": 1040
        },
        {
          "Kind": "eth0-rx",
          "Resource": "network_l2_network_Mbits_sec",
          "Min": 0.4755456,
          "Max": 8748.1233408,
          "Avg": 77.18037877982607,
          "Pct95": 4.672421888
        },
        {
          "Kind": "eth0-tx",
          "Resource": "network_l2_network_Mbits_sec",
          "Min": 0.04489216,
          "Max": 983.5995136,
          "Avg": 8.67289105808696,
          "Pct95": 0.327303168
        },
        {
          "Kind": "eth0-rx",
          "Resource": "network_l2_network_packets_sec",
          "Min": 28.2,
          "Max": 482739.5,
          "Avg": 4252.838260869566,
          "Pct95": 127.66999999999996
        },
        {
          "Kind": "eth0-tx",
          "Resource": "network_l2_network_packets_sec",
          "Min": 26,
          "Max": 313021.2,
          "Avg": 2769.8556521739133,
          "Pct95": 117.69999999999999
        }
      ]
    },
    {
      "Kind": "svt_infra_2",
      "Results": [
        {
          "Kind": "hyperkube_kubelet_",
          "Resource": "cpu_usage_percent_cpu",
          "Min": 1.7,
          "Max": 6.4,
          "Avg": 3.6435652173913042,
          "Pct95": 5.8
        },
        {
          "Kind": "prometheus_",
          "Resource": "cpu_usage_percent_cpu",
          "Min": 11.2,
          "Max": 33.7,
          "Avg": 18.765130434782602,
          "Pct95": 28.219999999999995
        },
        {
          "Kind": "systemd_--switched-root",
          "Resource": "cpu_usage_percent_cpu",
          "Min": 0,
          "Max": 0.6,
          "Avg": 0.01826086956521739,
          "Pct95": 0.1
        },
        {
          "Kind": "ovs-vswitchd_unix",
          "Resource": "cpu_usage_percent_cpu",
          "Min": 0.2,
          "Max": 0.8,
          "Avg": 0.3252173913043477,
          "Pct95": 0.4
        },
        {
          "Kind": "crio",
          "Resource": "cpu_usage_percent_cpu",
          "Min": 0,
          "Max": 0,
          "Avg": 0,
          "Pct95": 0
        },
        {
          "Kind": "nvme0n1-write",
          "Resource": "disk_IOPS",
          "Min": 0,
          "Max": 42.6,
          "Avg": 9.864260869565218,
          "Pct95": 28.23
        },
        {
          "Kind": "nvme0n1-read",
          "Resource": "disk_IOPS",
          "Min": 0,
          "Max": 0,
          "Avg": 0,
          "Pct95": 0
        },
        {
          "Kind": "hyperkube_kubelet_",
          "Resource": "memory_usage_resident_set_size",
          "Min": 186744,
          "Max": 191324,
          "Avg": 189238.5043478261,
          "Pct95": 191060
        },
        {
          "Kind": "prometheus_",
          "Resource": "memory_usage_resident_set_size",
          "Min": 1183704,
          "Max": 1375108,
          "Avg": 1239583.9652173913,
          "Pct95": 1320599.2
        },
        {
          "Kind": "systemd_--switched-root",
          "Resource": "memory_usage_resident_set_size",
          "Min": 7520,
          "Max": 7520,
          "Avg": 7520,
          "Pct95": 7520
        },
        {
          "Kind": "ovs-vswitchd_unix",
          "Resource": "memory_usage_resident_set_size",
          "Min": 60484,
          "Max": 60484,
          "Avg": 60484,
          "Pct95": 60484
        },
        {
          "Kind": "crio",
          "Resource": "memory_usage_resident_set_size",
          "Min": 1040,
          "Max": 1040,
          "Avg": 1040,
          "Pct95": 1040
        },
        {
          "Kind": "eth0-rx",
          "Resource": "network_l2_network_Mbits_sec",
          "Min": 13.13275904,
          "Max": 19.42929408,
          "Avg": 16.455474131478255,
          "Pct95": 17.817329664
        },
        {
          "Kind": "eth0-tx",
          "Resource": "network_l2_network_Mbits_sec",
          "Min": 0.17137664,
          "Max": 4.60128256,
          "Avg": 0.5110133982608696,
          "Pct95": 3.2525434879999997
        },
        {
          "Kind": "eth0-rx",
          "Resource": "network_l2_network_packets_sec",
          "Min": 325.5,
          "Max": 505.1,
          "Avg": 407.7113043478262,
          "Pct95": 480.55
        },
        {
          "Kind": "eth0-tx",
          "Resource": "network_l2_network_packets_sec",
          "Min": 172.9,
          "Max": 333,
          "Avg": 218.25913043478258,
          "Pct95": 287.15
        }
      ]
    },
    {
      "Kind": "svt_infra_3",
      "Results": [
        {
          "Kind": "hyperkube_kubelet_",
          "Resource": "cpu_usage_percent_cpu",
          "Min": 1.5,
          "Max": 7.3,
          "Avg": 3.123391304347825,
          "Pct95": 6.33
        },
        {
          "Kind": "systemd_--switched-root",
          "Resource": "cpu_usage_percent_cpu",
          "Min": 0,
          "Max": 0.3,
          "Avg": 0.008695652173913044,
          "Pct95": 0.029999999999999718
        },
        {
          "Kind": "ovs-vswitchd_unix",
          "Resource": "cpu_usage_percent_cpu",
          "Min": 0.1,
          "Max": 0.5,
          "Avg": 0.2608695652173912,
          "Pct95": 0.4
        },
        {
          "Kind": "crio",
          "Resource": "cpu_usage_percent_cpu",
          "Min": 0,
          "Max": 0,
          "Avg": 0,
          "Pct95": 0
        },
        {
          "Kind": "nvme0n1-write",
          "Resource": "disk_IOPS",
          "Min": 0,
          "Max": 42.9,
          "Avg": 7.658260869565217,
          "Pct95": 22.23
        },
        {
          "Kind": "nvme0n1-read",
          "Resource": "disk_IOPS",
          "Min": 0,
          "Max": 0,
          "Avg": 0,
          "Pct95": 0
        },
        {
          "Kind": "hyperkube_kubelet_",
          "Resource": "memory_usage_resident_set_size",
          "Min": 176744,
          "Max": 184712,
          "Avg": 181540.6608695652,
          "Pct95": 184712
        },
        {
          "Kind": "systemd_--switched-root",
          "Resource": "memory_usage_resident_set_size",
          "Min": 7380,
          "Max": 7380,
          "Avg": 7380,
          "Pct95": 7380
        },
        {
          "Kind": "ovs-vswitchd_unix",
          "Resource": "memory_usage_resident_set_size",
          "Min": 59972,
          "Max": 59972,
          "Avg": 59972,
          "Pct95": 59972
        },
        {
          "Kind": "crio",
          "Resource": "memory_usage_resident_set_size",
          "Min": 1040,
          "Max": 1040,
          "Avg": 1040,
          "Pct95": 1040
        },
        {
          "Kind": "eth0-rx",
          "Resource": "network_l2_network_Mbits_sec",
          "Min": 0.17424384,
          "Max": 3657.36574976,
          "Avg": 32.12471643269565,
          "Pct95": 0.77144064
        },
        {
          "Kind": "eth0-tx",
          "Resource": "network_l2_network_Mbits_sec",
          "Min": 0.01376256,
          "Max": 875.35386624,
          "Avg": 7.715363083130435,
          "Pct95": 0.236806144
        },
        {
          "Kind": "eth0-rx",
          "Resource": "network_l2_network_packets_sec",
          "Min": 17.4,
          "Max": 361640.4,
          "Avg": 3179.5513043478254,
          "Pct95": 71.42999999999998
        },
        {
          "Kind": "eth0-tx",
          "Resource": "network_l2_network_packets_sec",
          "Min": 14.4,
          "Max": 202359,
          "Avg": 1789.1295652173912,
          "Pct95": 60.129999999999995
        }
      ]
    },
    {
      "Kind": "svt_master_1_etcd_1",
      "Results": [
        {
          "Kind": "hyperkube_kubelet_",
          "Resource": "cpu_usage_percent_cpu",
          "Min": 2.4,
          "Max": 10.6,
          "Avg": 5.635478260869564,
          "Pct95": 8.916
        },
        {
          "Kind": "etcd",
          "Resource": "cpu_usage_percent_cpu",
          "Min": 8.5,
          "Max": 22.6,
          "Avg": 12.207652173913045,
          "Pct95": 17.859999999999996
        },
        {
          "Kind": "systemd_--switched-root",
          "Resource": "cpu_usage_percent_cpu",
          "Min": 0,
          "Max": 2.1,
          "Avg": 0.06869565217391303,
          "Pct95": 0.4199999999999988
        },
        {
          "Kind": "ovs-vswitchd_unix",
          "Resource": "cpu_usage_percent_cpu",
          "Min": 0.1,
          "Max": 1,
          "Avg": 0.25826086956521727,
          "Pct95": 0.4299999999999997
        },
        {
          "Kind": "crio",
          "Resource": "cpu_usage_percent_cpu",
          "Min": 0,
          "Max": 0.5,
          "Avg": 0.00608695652173913,
          "Pct95": 0
        },
        {
          "Kind": "nvme0n1-write",
          "Resource": "disk_IOPS",
          "Min": 65.7,
          "Max": 213,
          "Avg": 103.63486956521734,
          "Pct95": 162.48000000000002
        },
        {
          "Kind": "nvme0n1-read",
          "Resource": "disk_IOPS",
          "Min": 0,
          "Max": 0,
          "Avg": 0,
          "Pct95": 0
        },
        {
          "Kind": "hyperkube_kubelet_",
          "Resource": "memory_usage_resident_set_size",
          "Min": 335420,
          "Max": 352668,
          "Avg": 338026.6782608696,
          "Pct95": 352668
        },
        {
          "Kind": "etcd",
          "Resource": "memory_usage_resident_set_size",
          "Min": 270424,
          "Max": 388160,
          "Avg": 318213.07826086954,
          "Pct95": 388160
        },
        {
          "Kind": "systemd_--switched-root",
          "Resource": "memory_usage_resident_set_size",
          "Min": 8076,
          "Max": 8076,
          "Avg": 8076,
          "Pct95": 8076
        },
        {
          "Kind": "ovs-vswitchd_unix",
          "Resource": "memory_usage_resident_set_size",
          "Min": 60596,
          "Max": 60596,
          "Avg": 60596,
          "Pct95": 60596
        },
        {
          "Kind": "crio",
          "Resource": "memory_usage_resident_set_size",
          "Min": 0,
          "Max": 1044,
          "Avg": 199.72173913043477,
          "Pct95": 1044
        },
        {
          "Kind": "eth0-rx",
          "Resource": "network_l2_network_Mbits_sec",
          "Min": 1.78003968,
          "Max": 32709.56081152,
          "Avg": 288.7186563784348,
          "Pct95": 7.408615423999999
        },
        {
          "Kind": "eth0-tx",
          "Resource": "network_l2_network_Mbits_sec",
          "Min": 2.6877952,
          "Max": 86283.91018496,
          "Avg": 764.7694819506089,
          "Pct95": 20.210122751999997
        },
        {
          "Kind": "eth0-rx",
          "Resource": "network_l2_network_packets_sec",
          "Min": 1013.6,
          "Max": 9705210.3,
          "Avg": 85956.60582608695,
          "Pct95": 2571.3099999999995
        },
        {
          "Kind": "eth0-tx",
          "Resource": "network_l2_network_packets_sec",
          "Min": 1035,
          "Max": 10353787.4,
          "Avg": 91720.06208695655,
          "Pct95": 2656.5999999999995
        }
      ]
    },
    {
      "Kind": "svt_master_2_etcd_2",
      "Results": [
        {
          "Kind": "hyperkube_kubelet_",
          "Resource": "cpu_usage_percent_cpu",
          "Min": 2.6,
          "Max": 10.3,
          "Avg": 5.492869565217392,
          "Pct95": 8.9
        },
        {
          "Kind": "etcd",
          "Resource": "cpu_usage_percent_cpu",
          "Min": 6.4,
          "Max": 24.1,
          "Avg": 9.128521739130434,
          "Pct95": 15.709999999999997
        },
        {
          "Kind": "systemd_--switched-root",
          "Resource": "cpu_usage_percent_cpu",
          "Min": 0,
          "Max": 2.1,
          "Avg": 0.08086956521739129,
          "Pct95": 0.3899999999999991
        },
        {
          "Kind": "ovs-vswitchd_unix",
          "Resource": "cpu_usage_percent_cpu",
          "Min": 0.1,
          "Max": 1.2,
          "Avg": 0.274782608695652,
          "Pct95": 0.4
        },
        {
          "Kind": "crio",
          "Resource": "cpu_usage_percent_cpu",
          "Min": 0,
          "Max": 0,
          "Avg": 0,
          "Pct95": 0
        },
        {
          "Kind": "nvme0n1-write",
          "Resource": "disk_IOPS",
          "Min": 67.5,
          "Max": 218.2,
          "Avg": 104.44965217391305,
          "Pct95": 156.331
        },
        {
          "Kind": "nvme0n1-read",
          "Resource": "disk_IOPS",
          "Min": 0,
          "Max": 0,
          "Avg": 0,
          "Pct95": 0
        },
        {
          "Kind": "hyperkube_kubelet_",
          "Resource": "memory_usage_resident_set_size",
          "Min": 325740,
          "Max": 337624,
          "Avg": 328535.06086956523,
          "Pct95": 336592
        },
        {
          "Kind": "etcd",
          "Resource": "memory_usage_resident_set_size",
          "Min": 271996,
          "Max": 376604,
          "Avg": 321265.28695652174,
          "Pct95": 376420
        },
        {
          "Kind": "systemd_--switched-root",
          "Resource": "memory_usage_resident_set_size",
          "Min": 8252,
          "Max": 8252,
          "Avg": 8252,
          "Pct95": 8252
        },
        {
          "Kind": "ovs-vswitchd_unix",
          "Resource": "memory_usage_resident_set_size",
          "Min": 60448,
          "Max": 60448,
          "Avg": 60448,
          "Pct95": 60448
        },
        {
          "Kind": "crio",
          "Resource": "memory_usage_resident_set_size",
          "Min": 992,
          "Max": 992,
          "Avg": 992,
          "Pct95": 992
        },
        {
          "Kind": "eth0-rx",
          "Resource": "network_l2_network_Mbits_sec",
          "Min": 2.0164608,
          "Max": 74482.65474048,
          "Avg": 1311.3829194351301,
          "Pct95": 22.999588863999996
        },
        {
          "Kind": "eth0-tx",
          "Resource": "network_l2_network_Mbits_sec",
          "Min": 13.77017856,
          "Max": 123619.97819904,
          "Avg": 2168.138165381565,
          "Pct95": 27.648581632
        },
        {
          "Kind": "eth0-rx",
          "Resource": "network_l2_network_packets_sec",
          "Min": 1048.9,
          "Max": 10191579.3,
          "Avg": 178714.52034782612,
          "Pct95": 2505.0199999999995
        },
        {
          "Kind": "eth0-tx",
          "Resource": "network_l2_network_packets_sec",
          "Min": 1207.1,
          "Max": 10651602.4,
          "Avg": 186763.22591304354,
          "Pct95": 2543.3599999999997
        }
      ]
    },
    {
      "Kind": "svt_master_3_etcd_3",
      "Results": [
        {
          "Kind": "hyperkube_kubelet_",
          "Resource": "cpu_usage_percent_cpu",
          "Min": 2.7,
          "Max": 9.1,
          "Avg": 5.185130434782608,
          "Pct95": 7.56
        },
        {
          "Kind": "etcd",
          "Resource": "cpu_usage_percent_cpu",
          "Min": 5.2,
          "Max": 18,
          "Avg": 7.766782608695654,
          "Pct95": 10.16
        },
        {
          "Kind": "systemd_--switched-root",
          "Resource": "cpu_usage_percent_cpu",
          "Min": 0,
          "Max": 1.9,
          "Avg": 0.036521739130434785,
          "Pct95": 0.1
        },
        {
          "Kind": "ovs-vswitchd_unix",
          "Resource": "cpu_usage_percent_cpu",
          "Min": 0.1,
          "Max": 0.8,
          "Avg": 0.2626086956521738,
          "Pct95": 0.4
        },
        {
          "Kind": "crio",
          "Resource": "cpu_usage_percent_cpu",
          "Min": 0,
          "Max": 0,
          "Avg": 0,
          "Pct95": 0
        },
        {
          "Kind": "nvme0n1-write",
          "Resource": "disk_IOPS",
          "Min": 66.9,
          "Max": 184.2,
          "Avg": 102.13469565217397,
          "Pct95": 150.99
        },
        {
          "Kind": "nvme0n1-read",
          "Resource": "disk_IOPS",
          "Min": 0,
          "Max": 0,
          "Avg": 0,
          "Pct95": 0
        },
        {
          "Kind": "hyperkube_kubelet_",
          "Resource": "memory_usage_resident_set_size",
          "Min": 361764,
          "Max": 364740,
          "Avg": 362361.1130434783,
          "Pct95": 362931.6
        },
        {
          "Kind": "etcd",
          "Resource": "memory_usage_resident_set_size",
          "Min": 269452,
          "Max": 372556,
          "Avg": 312279.16521739133,
          "Pct95": 370926.4
        },
        {
          "Kind": "systemd_--switched-root",
          "Resource": "memory_usage_resident_set_size",
          "Min": 8092,
          "Max": 8092,
          "Avg": 8092,
          "Pct95": 8092
        },
        {
          "Kind": "ovs-vswitchd_unix",
          "Resource": "memory_usage_resident_set_size",
          "Min": 60480,
          "Max": 60480,
          "Avg": 60480,
          "Pct95": 60480
        },
        {
          "Kind": "crio",
          "Resource": "memory_usage_resident_set_size",
          "Min": 1036,
          "Max": 1036,
          "Avg": 1036,
          "Pct95": 1036
        },
        {
          "Kind": "eth0-rx",
          "Resource": "network_l2_network_Mbits_sec",
          "Min": 2.08003072,
          "Max": 23671.30394624,
          "Avg": 210.73447214747827,
          "Pct95": 23.300792319999996
        },
        {
          "Kind": "eth0-tx",
          "Resource": "network_l2_network_Mbits_sec",
          "Min": 6.18446848,
          "Max": 55709.4002688,
          "Avg": 494.7649779979131,
          "Pct95": 25.636560896
        },
        {
          "Kind": "eth0-rx",
          "Resource": "network_l2_network_packets_sec",
          "Min": 827.1,
          "Max": 7197020.9,
          "Avg": 63682.90139130434,
          "Pct95": 2193.8999999999996
        },
        {
          "Kind": "eth0-tx",
          "Resource": "network_l2_network_packets_sec",
          "Min": 904,
          "Max": 7659717,
          "Avg": 67794.97556521739,
          "Pct95": 2263.6699999999996
        }
      ]
    },
    {
      "Kind": "svt_node_1",
      "Results": [
        {
          "Kind": "hyperkube_kubelet_",
          "Resource": "cpu_usage_percent_cpu",
          "Min": 0,
          "Max": 25.2,
          "Avg": 8.78939655172414,
          "Pct95": 22.325
        },
        {
          "Kind": "systemd_--switched-root",
          "Resource": "cpu_usage_percent_cpu",
          "Min": 0,
          "Max": 10.69,
          "Avg": 1.0723275862068964,
          "Pct95": 6.85
        },
        {
          "Kind": "ovs-vswitchd_unix",
          "Resource": "cpu_usage_percent_cpu",
          "Min": 0,
          "Max": 7.9,
          "Avg": 0.7017241379310352,
          "Pct95": 3.9499999999999997
        },
        {
          "Kind": "crio",
          "Resource": "cpu_usage_percent_cpu",
          "Min": 0,
          "Max": 0,
          "Avg": 0,
          "Pct95": 0
        },
        {
          "Kind": "vda-write",
          "Resource": "disk_IOPS",
          "Min": 0,
          "Max": 117.6,
          "Avg": 29.04817391304348,
          "Pct95": 85.17999999999999
        },
        {
          "Kind": "vda-read",
          "Resource": "disk_IOPS",
          "Min": 0,
          "Max": 0.4,
          "Avg": 0.0034782608695652175,
          "Pct95": 0
        },
        {
          "Kind": "xvda-write",
          "Resource": "disk_IOPS",
          "Min": 0,
          "Max": 117.6,
          "Avg": 29.04817391304348,
          "Pct95": 85.17999999999999
        },
        {
          "Kind": "xvda-read",
          "Resource": "disk_IOPS",
          "Min": 0,
          "Max": 0.4,
          "Avg": 0.0034782608695652175,
          "Pct95": 0
        },
        {
          "Kind": "hyperkube_kubelet_",
          "Resource": "memory_usage_resident_set_size",
          "Min": 0,
          "Max": 319484,
          "Avg": 284456.2413793103,
          "Pct95": 319484
        },
        {
          "Kind": "systemd_--switched-root",
          "Resource": "memory_usage_resident_set_size",
          "Min": 0,
          "Max": 16704,
          "Avg": 16560,
          "Pct95": 16704
        },
        {
          "Kind": "ovs-vswitchd_unix",
          "Resource": "memory_usage_resident_set_size",
          "Min": 0,
          "Max": 46800,
          "Avg": 46396.55172413793,
          "Pct95": 46800
        },
        {
          "Kind": "crio",
          "Resource": "memory_usage_resident_set_size",
          "Min": 0,
          "Max": 1008,
          "Avg": 764.6896551724138,
          "Pct95": 1008
        },
        {
          "Kind": "eth0-rx",
          "Resource": "network_l2_network_Mbits_sec",
          "Min": 0,
          "Max": 0.38977536,
          "Avg": 0.02243112069565218,
          "Pct95": 0.12368281599999999
        },
        {
          "Kind": "eth0-tx",
          "Resource": "network_l2_network_Mbits_sec",
          "Min": 0,
          "Max": 0.03571712,
          "Avg": 0.0031044118260869563,
          "Pct95": 0.030326783999999996
        },
        {
          "Kind": "eth0-rx",
          "Resource": "network_l2_network_packets_sec",
          "Min": 0,
          "Max": 36.5,
          "Avg": 2.284347826086957,
          "Pct95": 13.93
        },
        {
          "Kind": "eth0-tx",
          "Resource": "network_l2_network_packets_sec",
          "Min": 0,
          "Max": 26,
          "Avg": 1.8356521739130434,
          "Pct95": 11.39
        }
      ]
    },
    {
      "Kind": "svt_node_2",
      "Results": [
        {
          "Kind": "hyperkube_kubelet_",
          "Resource": "cpu_usage_percent_cpu",
          "Min": 0,
          "Max": 26,
          "Avg": 9.073534482758623,
          "Pct95": 22.75
        },
        {
          "Kind": "systemd_--switched-root",
          "Resource": "cpu_usage_percent_cpu",
          "Min": 0,
          "Max": 11.79,
          "Avg": 1.039396551724138,
          "Pct95": 6.3
        },
        {
          "Kind": "ovs-vswitchd_unix",
          "Resource": "cpu_usage_percent_cpu",
          "Min": 0,
          "Max": 8.3,
          "Avg": 0.6973275862068968,
          "Pct95": 4.55
        },
        {
          "Kind": "crio",
          "Resource": "cpu_usage_percent_cpu",
          "Min": 0,
          "Max": 0,
          "Avg": 0,
          "Pct95": 0
        },
        {
          "Kind": "vda-write",
          "Resource": "disk_IOPS",
          "Min": 0,
          "Max": 120.1,
          "Avg": 28.460434782608697,
          "Pct95": 87.32
        },
        {
          "Kind": "vda-read",
          "Resource": "disk_IOPS",
          "Min": 0,
          "Max": 0,
          "Avg": 0,
          "Pct95": 0
        },
        {
          "Kind": "xvda-write",
          "Resource": "disk_IOPS",
          "Min": 0,
          "Max": 120.1,
          "Avg": 28.460434782608697,
          "Pct95": 87.32
        },
        {
          "Kind": "xvda-read",
          "Resource": "disk_IOPS",
          "Min": 0,
          "Max": 0,
          "Avg": 0,
          "Pct95": 0
        },
        {
          "Kind": "hyperkube_kubelet_",
          "Resource": "memory_usage_resident_set_size",
          "Min": 0,
          "Max": 317048,
          "Avg": 281146.2413793103,
          "Pct95": 316454
        },
        {
          "Kind": "systemd_--switched-root",
          "Resource": "memory_usage_resident_set_size",
          "Min": 0,
          "Max": 16400,
          "Avg": 16258.620689655172,
          "Pct95": 16400
        },
        {
          "Kind": "ovs-vswitchd_unix",
          "Resource": "memory_usage_resident_set_size",
          "Min": 0,
          "Max": 46800,
          "Avg": 46396.55172413793,
          "Pct95": 46800
        },
        {
          "Kind": "crio",
          "Resource": "memory_usage_resident_set_size",
          "Min": 0,
          "Max": 1000,
          "Avg": 224.13793103448276,
          "Pct95": 1000
        },
        {
          "Kind": "eth0-rx",
          "Resource": "network_l2_network_Mbits_sec",
          "Min": 0,
          "Max": 0.37855232,
          "Avg": 0.022388379826086952,
          "Pct95": 0.12199526399999999
        },
        {
          "Kind": "eth0-tx",
          "Resource": "network_l2_network_Mbits_sec",
          "Min": 0,
          "Max": 0.17948672,
          "Avg": 0.004514860521739131,
          "Pct95": 0.02650931199999998
        },
        {
          "Kind": "eth0-rx",
          "Resource": "network_l2_network_packets_sec",
          "Min": 0,
          "Max": 35.1,
          "Avg": 2.3156521739130436,
          "Pct95": 13.729999999999997
        },
        {
          "Kind": "eth0-tx",
          "Resource": "network_l2_network_packets_sec",
          "Min": 0,
          "Max": 25,
          "Avg": 1.8800000000000003,
          "Pct95": 11.549999999999999
        }
      ]
    }
  ],
  "Metrics": null
}
