{
  "Hosts": [
    {
      "Kind": "svt_cns_1",
      "Results": [
        {
          "Kind": "hyperkube_kubelet_",
          "Resource": "cpu_usage_percent_cpu",
          "Min": 2.1,
          "Max": 4.1,
          "Avg": 2.986,
          "Pct95": 4.1
        },
        {
          "Kind": "dockerd-current_",
          "Resource": "cpu_usage_percent_cpu",
          "Min": 0.6,
          "Max": 2.5,
          "Avg": 0.9333333333333335,
          "Pct95": 1.4499999999999984
        },
        {
          "Kind": "systemd_--switched-root",
          "Resource": "cpu_usage_percent_cpu",
          "Min": 0,
          "Max": 0.5,
          "Avg": 0.05333333333333333,
          "Pct95": 0.21999999999999958
        },
        {
          "Kind": "openshift_start_network_",
          "Resource": "cpu_usage_percent_cpu",
          "Min": 0.1,
          "Max": 1.6,
          "Avg": 0.5,
          "Pct95": 1.0399999999999991
        },
        {
          "Kind": "ovs-vswitchd_unix",
          "Resource": "cpu_usage_percent_cpu",
          "Min": 0,
          "Max": 0.5,
          "Avg": 0.14666666666666667,
          "Pct95": 0.35999999999999976
        },
        {
          "Kind": "vda-write",
          "Resource": "disk_IOPS",
          "Min": 12.8,
          "Max": 41.6,
          "Avg": 22.873333333333335,
          "Pct95": 32.98999999999999
        },
        {
          "Kind": "vda-read",
          "Resource": "disk_IOPS",
          "Min": 0,
          "Max": 2.2,
          "Avg": 0.16000000000000003,
          "Pct95": 0.7299999999999978
        },
        {
          "Kind": "nvme0n1-write",
          "Resource": "disk_IOPS",
          "Min": 0,
          "Max": 2.2,
          "Avg": 0.5733333333333335,
          "Pct95": 1.7799999999999994
        },
        {
          "Kind": "nvme0n1-read",
          "Resource": "disk_IOPS",
          "Min": 0,
          "Max": 0,
          "Avg": 0,
          "Pct95": 0
        },
        {
          "Kind": "hyperkube_kubelet_",
          "Resource": "memory_usage_resident_set_size",
          "Min": 135256,
          "Max": 135556,
          "Avg": 135356,
          "Pct95": 135556
        },
        {
          "Kind": "dockerd-current_",
          "Resource": "memory_usage_resident_set_size",
          "Min": 78140,
          "Max": 80188,
          "Avg": 79232.26666666666,
          "Pct95": 80188
        },
        {
          "Kind": "systemd_--switched-root",
          "Resource": "memory_usage_resident_set_size",
          "Min": 8720,
          "Max": 8720,
          "Avg": 8720,
          "Pct95": 8720
        },
        {
          "Kind": "openshift_start_network_",
          "Resource": "memory_usage_resident_set_size",
          "Min": 147916,
          "Max": 152540,
          "Avg": 150690.4,
          "Pct95": 152540
        },
        {
          "Kind": "ovs-vswitchd_unix",
          "Resource": "memory_usage_resident_set_size",
          "Min": 145616,
          "Max": 145620,
          "Avg": 145619.73333333334,
          "Pct95": 145620
        },
        {
          "Kind": "eth0-rx",
          "Resource": "network_l2_network_Mbits_sec",
          "Min": 0.13205504,
          "Max": 1323089.69668608,
          "Avg": 88301.24709751466,
          "Pct95": 397025.93033830257
        },
        {
          "Kind": "eth0-tx",
          "Resource": "network_l2_network_Mbits_sec",
          "Min": 8.4865024,
          "Max": 159047.63273216,
          "Avg": 10627.066740736003,
          "Pct95": 47738.04462899183
        },
        {
          "Kind": "eth0-rx",
          "Resource": "network_l2_network_packets_sec",
          "Min": 154.4,
          "Max": 54943591.1,
          "Avg": 3676900.1399999997,
          "Pct95": 16497462.959999943
        },
        {
          "Kind": "eth0-tx",
          "Resource": "network_l2_network_packets_sec",
          "Min": 104.2,
          "Max": 57386177.1,
          "Avg": 3844914.7599999993,
          "Pct95": 17235964.75999994
        }
      ]
    },
    {
      "Kind": "svt_cns_2",
      "Results": [
        {
          "Kind": "hyperkube_kubelet_",
          "Resource": "cpu_usage_percent_cpu",
          "Min": 1.7,
          "Max": 5.3,
          "Avg": 2.9466666666666668,
          "Pct95": 5.09
        },
        {
          "Kind": "dockerd-current_",
          "Resource": "cpu_usage_percent_cpu",
          "Min": 0.6,
          "Max": 1,
          "Avg": 0.7466666666666667,
          "Pct95": 0.9299999999999999
        },
        {
          "Kind": "systemd_--switched-root",
          "Resource": "cpu_usage_percent_cpu",
          "Min": 0,
          "Max": 0.2,
          "Avg": 0.02666666666666667,
          "Pct95": 0.1299999999999999
        },
        {
          "Kind": "openshift_start_network_",
          "Resource": "cpu_usage_percent_cpu",
          "Min": 0.1,
          "Max": 0.9,
          "Avg": 0.5133333333333334,
          "Pct95": 0.9000000000000001
        },
        {
          "Kind": "ovs-vswitchd_unix",
          "Resource": "cpu_usage_percent_cpu",
          "Min": 0,
          "Max": 0.3,
          "Avg": 0.09333333333333335,
          "Pct95": 0.22999999999999987
        },
        {
          "Kind": "vda-write",
          "Resource": "disk_IOPS",
          "Min": 12.1,
          "Max": 21.9,
          "Avg": 16.33866666666667,
          "Pct95": 21.48
        },
        {
          "Kind": "vda-read",
          "Resource": "disk_IOPS",
          "Min": 0,
          "Max": 0,
          "Avg": 0,
          "Pct95": 0
        },
        {
          "Kind": "nvme0n1-write",
          "Resource": "disk_IOPS",
          "Min": 0.1,
          "Max": 2.2,
          "Avg": 0.5733333333333335,
          "Pct95": 1.7799999999999994
        },
        {
          "Kind": "nvme0n1-read",
          "Resource": "disk_IOPS",
          "Min": 0,
          "Max": 0,
          "Avg": 0,
          "Pct95": 0
        },
        {
          "Kind": "hyperkube_kubelet_",
          "Resource": "memory_usage_resident_set_size",
          "Min": 133700,
          "Max": 133940,
          "Avg": 133759.73333333334,
          "Pct95": 133940
        },
        {
          "Kind": "dockerd-current_",
          "Resource": "memory_usage_resident_set_size",
          "Min": 68944,
          "Max": 68944,
          "Avg": 68944,
          "Pct95": 68944
        },
        {
          "Kind": "systemd_--switched-root",
          "Resource": "memory_usage_resident_set_size",
          "Min": 8544,
          "Max": 8544,
          "Avg": 8544,
          "Pct95": 8544
        },
        {
          "Kind": "openshift_start_network_",
          "Resource": "memory_usage_resident_set_size",
          "Min": 139520,
          "Max": 150296,
          "Avg": 146038.4,
          "Pct95": 150296
        },
        {
          "Kind": "ovs-vswitchd_unix",
          "Resource": "memory_usage_resident_set_size",
          "Min": 145416,
          "Max": 145416,
          "Avg": 145416,
          "Pct95": 145416
        },
        {
          "Kind": "eth0-rx",
          "Resource": "network_l2_network_Mbits_sec",
          "Min": 0.03104768,
          "Max": 0.16859136,
          "Avg": 0.05894417066666667,
          "Pct95": 0.11640831999999993
        },
        {
          "Kind": "eth0-tx",
          "Resource": "network_l2_network_Mbits_sec",
          "Min": 0.01368064,
          "Max": 0.1028096,
          "Avg": 0.05521407999999999,
          "Pct95": 0.09288908799999998
        },
        {
          "Kind": "eth0-rx",
          "Resource": "network_l2_network_packets_sec",
          "Min": 12.1,
          "Max": 28.4,
          "Avg": 17.886666666666667,
          "Pct95": 28.33
        },
        {
          "Kind": "eth0-tx",
          "Resource": "network_l2_network_packets_sec",
          "Min": 9.3,
          "Max": 23.9,
          "Avg": 14.120000000000001,
          "Pct95": 23.269999999999996
        }
      ]
    },
    {
      "Kind": "svt_cns_3",
      "Results": [
        {
          "Kind": "hyperkube_kubelet_",
          "Resource": "cpu_usage_percent_cpu",
          "Min": 2.3,
          "Max": 5.1,
          "Avg": 3.572666666666666,
          "Pct95": 5.1
        },
        {
          "Kind": "dockerd-current_",
          "Resource": "cpu_usage_percent_cpu",
          "Min": 0.6,
          "Max": 1.3,
          "Avg": 0.9266666666666669,
          "Pct95": 1.16
        },
        {
          "Kind": "systemd_--switched-root",
          "Resource": "cpu_usage_percent_cpu",
          "Min": 0,
          "Max": 0.1,
          "Avg": 0.020000000000000004,
          "Pct95": 0.1
        },
        {
          "Kind": "openshift_start_network_",
          "Resource": "cpu_usage_percent_cpu",
          "Min": 0.1,
          "Max": 0.8,
          "Avg": 0.48666666666666664,
          "Pct95": 0.8
        },
        {
          "Kind": "ovs-vswitchd_unix",
          "Resource": "cpu_usage_percent_cpu",
          "Min": 0,
          "Max": 0.2,
          "Avg": 0.12666666666666668,
          "Pct95": 0.2
        },
        {
          "Kind": "vda-write",
          "Resource": "disk_IOPS",
          "Min": 12.5,
          "Max": 21.5,
          "Avg": 17.28666666666667,
          "Pct95": 21.29
        },
        {
          "Kind": "vda-read",
          "Resource": "disk_IOPS",
          "Min": 0,
          "Max": 0,
          "Avg": 0,
          "Pct95": 0
        },
        {
          "Kind": "nvme0n1-write",
          "Resource": "disk_IOPS",
          "Min": 0.1,
          "Max": 3.6,
          "Avg": 0.9066666666666666,
          "Pct95": 2.829999999999999
        },
        {
          "Kind": "nvme0n1-read",
          "Resource": "disk_IOPS",
          "Min": 0,
          "Max": 0,
          "Avg": 0,
          "Pct95": 0
        },
        {
          "Kind": "hyperkube_kubelet_",
          "Resource": "memory_usage_resident_set_size",
          "Min": 137700,
          "Max": 137700,
          "Avg": 137700,
          "Pct95": 137700
        },
        {
          "Kind": "dockerd-current_",
          "Resource": "memory_usage_resident_set_size",
          "Min": 73948,
          "Max": 74740,
          "Avg": 74634.4,
          "Pct95": 74740
        },
        {
          "Kind": "systemd_--switched-root",
          "Resource": "memory_usage_resident_set_size",
          "Min": 8336,
          "Max": 8336,
          "Avg": 8336,
          "Pct95": 8336
        },
        {
          "Kind": "openshift_start_network_",
          "Resource": "memory_usage_resident_set_size",
          "Min": 142980,
          "Max": 151868,
          "Avg": 148312.8,
          "Pct95": 151868
        },
        {
          "Kind": "ovs-vswitchd_unix",
          "Resource": "memory_usage_resident_set_size",
          "Min": 145680,
          "Max": 145680,
          "Avg": 145680,
          "Pct95": 145680
        },
        {
          "Kind": "eth0-rx",
          "Resource": "network_l2_network_Mbits_sec",
          "Min": 0.04431872,
          "Max": 0.17604608,
          "Avg": 0.08491281066666666,
          "Pct95": 0.14060748799999995
        },
        {
          "Kind": "eth0-tx",
          "Resource": "network_l2_network_Mbits_sec",
          "Min": 0.03588096,
          "Max": 0.26075136,
          "Avg": 0.11176618666666666,
          "Pct95": 0.21797273599999992
        },
        {
          "Kind": "eth0-rx",
          "Resource": "network_l2_network_packets_sec",
          "Min": 19.2,
          "Max": 41.7,
          "Avg": 27.946666666666665,
          "Pct95": 40.86
        },
        {
          "Kind": "eth0-tx",
          "Resource": "network_l2_network_packets_sec",
          "Min": 15.2,
          "Max": 36.8,
          "Avg": 23.246666666666666,
          "Pct95": 36.379999999999995
        }
      ]
    },
    {
      "Kind": "svt_infra_1",
      "Results": [
        {
          "Kind": "hyperkube_kubelet_",
          "Resource": "cpu_usage_percent_cpu",
          "Min": 4.1,
          "Max": 92.91,
          "Avg": 10.614,
          "Pct95": 31.512999999999906
        },
        {
          "Kind": "dockerd-current_",
          "Resource": "cpu_usage_percent_cpu",
          "Min": 1.4,
          "Max": 2,
          "Avg": 1.6733333333333331,
          "Pct95": 2
        },
        {
          "Kind": "elasticsearc",
          "Resource": "cpu_usage_percent_cpu",
          "Min": 1.4,
          "Max": 3,
          "Avg": 2.1600000000000006,
          "Pct95": 2.9299999999999997
        },
        {
          "Kind": "systemd_--switched-root",
          "Resource": "cpu_usage_percent_cpu",
          "Min": 0,
          "Max": 0.1,
          "Avg": 0.020000000000000004,
          "Pct95": 0.1
        },
        {
          "Kind": "openshift_start_network_",
          "Resource": "cpu_usage_percent_cpu",
          "Min": 0.1,
          "Max": 1,
          "Avg": 0.4800000000000001,
          "Pct95": 0.9299999999999999
        },
        {
          "Kind": "ovs-vswitchd_unix",
          "Resource": "cpu_usage_percent_cpu",
          "Min": 0.1,
          "Max": 0.8,
          "Avg": 0.4066666666666666,
          "Pct95": 0.6599999999999998
        },
        {
          "Kind": "openshift-router",
          "Resource": "cpu_usage_percent_cpu",
          "Min": 0.1,
          "Max": 22,
          "Avg": 3.086666666666667,
          "Pct95": 21.159999999999997
        },
        {
          "Kind": "sda-write",
          "Resource": "disk_IOPS",
          "Min": 0,
          "Max": 1.3,
          "Avg": 0.22666666666666668,
          "Pct95": 0.9499999999999995
        },
        {
          "Kind": "sda-read",
          "Resource": "disk_IOPS",
          "Min": 0,
          "Max": 0,
          "Avg": 0,
          "Pct95": 0
        },
        {
          "Kind": "vda-write",
          "Resource": "disk_IOPS",
          "Min": 0,
          "Max": 13.2,
          "Avg": 2.7133333333333334,
          "Pct95": 6.47999999999999
        },
        {
          "Kind": "vda-read",
          "Resource": "disk_IOPS",
          "Min": 0,
          "Max": 0,
          "Avg": 0,
          "Pct95": 0
        },
        {
          "Kind": "nvme0n1-write",
          "Resource": "disk_IOPS",
          "Min": 0,
          "Max": 0,
          "Avg": 0,
          "Pct95": 0
        },
        {
          "Kind": "nvme0n1-read",
          "Resource": "disk_IOPS",
          "Min": 0,
          "Max": 0,
          "Avg": 0,
          "Pct95": 0
        },
        {
          "Kind": "hyperkube_kubelet_",
          "Resource": "memory_usage_resident_set_size",
          "Min": 163336,
          "Max": 163508,
          "Avg": 163393.33333333334,
          "Pct95": 163508
        },
        {
          "Kind": "dockerd-current_",
          "Resource": "memory_usage_resident_set_size",
          "Min": 95884,
          "Max": 96444,
          "Avg": 96257.33333333333,
          "Pct95": 96444
        },
        {
          "Kind": "elasticsearc",
          "Resource": "memory_usage_resident_set_size",
          "Min": 4293276,
          "Max": 4293276,
          "Avg": 4293276,
          "Pct95": 4293276
        },
        {
          "Kind": "systemd_--switched-root",
          "Resource": "memory_usage_resident_set_size",
          "Min": 9832,
          "Max": 9832,
          "Avg": 9832,
          "Pct95": 9832
        },
        {
          "Kind": "openshift_start_network_",
          "Resource": "memory_usage_resident_set_size",
          "Min": 149696,
          "Max": 159760,
          "Avg": 156405.33333333334,
          "Pct95": 159760
        },
        {
          "Kind": "ovs-vswitchd_unix",
          "Resource": "memory_usage_resident_set_size",
          "Min": 156200,
          "Max": 156200,
          "Avg": 156200,
          "Pct95": 156200
        },
        {
          "Kind": "openshift-router",
          "Resource": "memory_usage_resident_set_size",
          "Min": 278696,
          "Max": 278696,
          "Avg": 278696,
          "Pct95": 278696
        },
        {
          "Kind": "eth0-rx",
          "Resource": "network_l2_network_Mbits_sec",
          "Min": 0.20209664,
          "Max": 179.67415296,
          "Avg": 119.78374075733336,
          "Pct95": 174.38285004799997
        },
        {
          "Kind": "eth0-tx",
          "Resource": "network_l2_network_Mbits_sec",
          "Min": 2.82877952,
          "Max": 200.68245504,
          "Avg": 146.34053358933332,
          "Pct95": 194.403745792
        },
        {
          "Kind": "eth0-rx",
          "Resource": "network_l2_network_packets_sec",
          "Min": 109.1,
          "Max": 52937.1,
          "Avg": 35439.64,
          "Pct95": 51235.81999999999
        },
        {
          "Kind": "eth0-tx",
          "Resource": "network_l2_network_packets_sec",
          "Min": 133.2,
          "Max": 42980.2,
          "Avg": 29889.520000000004,
          "Pct95": 41719.57
        }
      ]
    },
    {
      "Kind": "svt_infra_2",
      "Results": [
        {
          "Kind": "hyperkube_kubelet_",
          "Resource": "cpu_usage_percent_cpu",
          "Min": 3.9,
          "Max": 100.9,
          "Avg": 11.313333333333334,
          "Pct95": 34.9599999999999
        },
        {
          "Kind": "dockerd-current_",
          "Resource": "cpu_usage_percent_cpu",
          "Min": 1.7,
          "Max": 2.59,
          "Avg": 2.0126666666666666,
          "Pct95": 2.3869999999999996
        },
        {
          "Kind": "elasticsearc",
          "Resource": "cpu_usage_percent_cpu",
          "Min": 1.6,
          "Max": 2,
          "Avg": 1.8599999999999999,
          "Pct95": 2
        },
        {
          "Kind": "systemd_--switched-root",
          "Resource": "cpu_usage_percent_cpu",
          "Min": 0,
          "Max": 0.1,
          "Avg": 0.02666666666666667,
          "Pct95": 0.1
        },
        {
          "Kind": "openshift_start_network_",
          "Resource": "cpu_usage_percent_cpu",
          "Min": 0.2,
          "Max": 1.4,
          "Avg": 0.6266666666666668,
          "Pct95": 1.1199999999999997
        },
        {
          "Kind": "ovs-vswitchd_unix",
          "Resource": "cpu_usage_percent_cpu",
          "Min": 0.1,
          "Max": 0.3,
          "Avg": 0.19333333333333333,
          "Pct95": 0.3
        },
        {
          "Kind": "openshift-router",
          "Resource": "cpu_usage_percent_cpu",
          "Min": 0.2,
          "Max": 21.2,
          "Avg": 3.1133333333333346,
          "Pct95": 21.06
        },
        {
          "Kind": "sda-write",
          "Resource": "disk_IOPS",
          "Min": 0,
          "Max": 0,
          "Avg": 0,
          "Pct95": 0
        },
        {
          "Kind": "sda-read",
          "Resource": "disk_IOPS",
          "Min": 0,
          "Max": 0,
          "Avg": 0,
          "Pct95": 0
        },
        {
          "Kind": "vda-write",
          "Resource": "disk_IOPS",
          "Min": 0,
          "Max": 9.6,
          "Avg": 2.26,
          "Pct95": 5.959999999999995
        },
        {
          "Kind": "vda-read",
          "Resource": "disk_IOPS",
          "Min": 0,
          "Max": 0,
          "Avg": 0,
          "Pct95": 0
        },
        {
          "Kind": "nvme0n1-write",
          "Resource": "disk_IOPS",
          "Min": 0,
          "Max": 0,
          "Avg": 0,
          "Pct95": 0
        },
        {
          "Kind": "nvme0n1-read",
          "Resource": "disk_IOPS",
          "Min": 0,
          "Max": 0,
          "Avg": 0,
          "Pct95": 0
        },
        {
          "Kind": "hyperkube_kubelet_",
          "Resource": "memory_usage_resident_set_size",
          "Min": 157580,
          "Max": 157960,
          "Avg": 157765.33333333334,
          "Pct95": 157873.2
        },
        {
          "Kind": "dockerd-current_",
          "Resource": "memory_usage_resident_set_size",
          "Min": 103452,
          "Max": 103452,
          "Avg": 103452,
          "Pct95": 103452
        },
        {
          "Kind": "elasticsearc",
          "Resource": "memory_usage_resident_set_size",
          "Min": 4257196,
          "Max": 4257196,
          "Avg": 4257196,
          "Pct95": 4257196
        },
        {
          "Kind": "systemd_--switched-root",
          "Resource": "memory_usage_resident_set_size",
          "Min": 9764,
          "Max": 9764,
          "Avg": 9764,
          "Pct95": 9764
        },
        {
          "Kind": "openshift_start_network_",
          "Resource": "memory_usage_resident_set_size",
          "Min": 151300,
          "Max": 159844,
          "Avg": 156426.4,
          "Pct95": 159844
        },
        {
          "Kind": "ovs-vswitchd_unix",
          "Resource": "memory_usage_resident_set_size",
          "Min": 151728,
          "Max": 151728,
          "Avg": 151728,
          "Pct95": 151728
        },
        {
          "Kind": "openshift-router",
          "Resource": "memory_usage_resident_set_size",
          "Min": 257848,
          "Max": 285776,
          "Avg": 267004.26666666666,
          "Pct95": 285776
        },
        {
          "Kind": "eth0-rx",
          "Resource": "network_l2_network_Mbits_sec",
          "Min": 0.11853824,
          "Max": 2.14048768,
          "Avg": 0.3035845973333334,
          "Pct95": 0.824041471999998
        },
        {
          "Kind": "eth0-tx",
          "Resource": "network_l2_network_Mbits_sec",
          "Min": 2.33832448,
          "Max": 168.60110848,
          "Avg": 13.787977045333333,
          "Pct95": 52.54476595199982
        },
        {
          "Kind": "eth0-rx",
          "Resource": "network_l2_network_packets_sec",
          "Min": 70.1,
          "Max": 3733.9,
          "Avg": 332.0533333333333,
          "Pct95": 1195.069999999996
        },
        {
          "Kind": "eth0-tx",
          "Resource": "network_l2_network_packets_sec",
          "Min": 88.3,
          "Max": 15812.2,
          "Avg": 1157.8800000000006,
          "Pct95": 4829.339999999984
        }
      ]
    },
    {
      "Kind": "svt_infra_3",
      "Results": [
        {
          "Kind": "hyperkube_kubelet_",
          "Resource": "cpu_usage_percent_cpu",
          "Min": 3.5,
          "Max": 94.81,
          "Avg": 11.080666666666666,
          "Pct95": 33.482999999999905
        },
        {
          "Kind": "dockerd-current_",
          "Resource": "cpu_usage_percent_cpu",
          "Min": 2.1,
          "Max": 3.09,
          "Avg": 2.252666666666667,
          "Pct95": 2.6069999999999993
        },
        {
          "Kind": "elasticsearc",
          "Resource": "cpu_usage_percent_cpu",
          "Min": 1.4,
          "Max": 2,
          "Avg": 1.6599999999999997,
          "Pct95": 1.8599999999999999
        },
        {
          "Kind": "prometheus_",
          "Resource": "cpu_usage_percent_cpu",
          "Min": 58.4,
          "Max": 448.1,
          "Avg": 133.84533333333334,
          "Pct95": 437.95000000000005
        },
        {
          "Kind": "systemd_--switched-root",
          "Resource": "cpu_usage_percent_cpu",
          "Min": 0,
          "Max": 0.1,
          "Avg": 0.02666666666666667,
          "Pct95": 0.1
        },
        {
          "Kind": "openshift_start_network_",
          "Resource": "cpu_usage_percent_cpu",
          "Min": 0.2,
          "Max": 1,
          "Avg": 0.5866666666666667,
          "Pct95": 0.9299999999999999
        },
        {
          "Kind": "ovs-vswitchd_unix",
          "Resource": "cpu_usage_percent_cpu",
          "Min": 0.1,
          "Max": 0.4,
          "Avg": 0.24000000000000002,
          "Pct95": 0.3299999999999999
        },
        {
          "Kind": "openshift-router",
          "Resource": "cpu_usage_percent_cpu",
          "Min": 0.1,
          "Max": 21.2,
          "Avg": 3.233333333333334,
          "Pct95": 20.849999999999998
        },
        {
          "Kind": "kibana",
          "Resource": "cpu_usage_percent_cpu",
          "Min": 0.7,
          "Max": 1.5,
          "Avg": 1.0266666666666666,
          "Pct95": 1.4299999999999997
        },
        {
          "Kind": "sda-write",
          "Resource": "disk_IOPS",
          "Min": 0,
          "Max": 0,
          "Avg": 0,
          "Pct95": 0
        },
        {
          "Kind": "sda-read",
          "Resource": "disk_IOPS",
          "Min": 0,
          "Max": 0,
          "Avg": 0,
          "Pct95": 0
        },
        {
          "Kind": "vda-write",
          "Resource": "disk_IOPS",
          "Min": 3.8,
          "Max": 11.7,
          "Avg": 6.499999999999999,
          "Pct95": 10.089999999999996
        },
        {
          "Kind": "vda-read",
          "Resource": "disk_IOPS",
          "Min": 0,
          "Max": 8.1,
          "Avg": 0.5399999999999999,
          "Pct95": 2.4299999999999913
        },
        {
          "Kind": "nvme0n1-write",
          "Resource": "disk_IOPS",
          "Min": 0,
          "Max": 0,
          "Avg": 0,
          "Pct95": 0
        },
        {
          "Kind": "nvme0n1-read",
          "Resource": "disk_IOPS",
          "Min": 0,
          "Max": 0,
          "Avg": 0,
          "Pct95": 0
        },
        {
          "Kind": "hyperkube_kubelet_",
          "Resource": "memory_usage_resident_set_size",
          "Min": 163576,
          "Max": 163888,
          "Avg": 163853.6,
          "Pct95": 163888
        },
        {
          "Kind": "dockerd-current_",
          "Resource": "memory_usage_resident_set_size",
          "Min": 99136,
          "Max": 99136,
          "Avg": 99136,
          "Pct95": 99136
        },
        {
          "Kind": "elasticsearc",
          "Resource": "memory_usage_resident_set_size",
          "Min": 4221988,
          "Max": 4221988,
          "Avg": 4221988,
          "Pct95": 4221988
        },
        {
          "Kind": "prometheus_",
          "Resource": "memory_usage_resident_set_size",
          "Min": 20483980,
          "Max": 20580764,
          "Avg": 20525387.466666665,
          "Pct95": 20558504
        },
        {
          "Kind": "systemd_--switched-root",
          "Resource": "memory_usage_resident_set_size",
          "Min": 9752,
          "Max": 9752,
          "Avg": 9752,
          "Pct95": 9752
        },
        {
          "Kind": "openshift_start_network_",
          "Resource": "memory_usage_resident_set_size",
          "Min": 153044,
          "Max": 159300,
          "Avg": 156885.6,
          "Pct95": 159300
        },
        {
          "Kind": "ovs-vswitchd_unix",
          "Resource": "memory_usage_resident_set_size",
          "Min": 150808,
          "Max": 150808,
          "Avg": 150808,
          "Pct95": 150808
        },
        {
          "Kind": "openshift-router",
          "Resource": "memory_usage_resident_set_size",
          "Min": 263852,
          "Max": 263852,
          "Avg": 263852,
          "Pct95": 263852
        },
        {
          "Kind": "kibana",
          "Resource": "memory_usage_resident_set_size",
          "Min": 78808,
          "Max": 86056,
          "Avg": 82787.2,
          "Pct95": 85745.2
        },
        {
          "Kind": "eth0-rx",
          "Resource": "network_l2_network_Mbits_sec",
          "Min": 12.8086016,
          "Max": 18.01723904,
          "Avg": 14.258869589333331,
          "Pct95": 17.415528448
        },
        {
          "Kind": "eth0-tx",
          "Resource": "network_l2_network_Mbits_sec",
          "Min": 3.6233216,
          "Max": 169.00292608,
          "Avg": 14.693367808,
          "Pct95": 53.31020185599983
        },
        {
          "Kind": "eth0-rx",
          "Resource": "network_l2_network_packets_sec",
          "Min": 542.6,
          "Max": 4312.1,
          "Avg": 818.9533333333333,
          "Pct95": 1715.029999999996
        },
        {
          "Kind": "eth0-tx",
          "Resource": "network_l2_network_packets_sec",
          "Min": 554.6,
          "Max": 15400.1,
          "Avg": 1573.88,
          "Pct95": 5058.159999999984
        }
      ]
    },
    {
      "Kind": "svt_master_1_etcd_1",
      "Results": [
        {
          "Kind": "openshift_start_master_api_",
          "Resource": "cpu_usage_percent_cpu",
          "Min": 8.4,
          "Max": 69.76,
          "Avg": 20.257333333333335,
          "Pct95": 59.28799999999998
        },
        {
          "Kind": "openshift_start_master_controllers_",
          "Resource": "cpu_usage_percent_cpu",
          "Min": 1.8,
          "Max": 3.8,
          "Avg": 2.3,
          "Pct95": 3.7299999999999995
        },
        {
          "Kind": "hyperkube_kubelet_",
          "Resource": "cpu_usage_percent_cpu",
          "Min": 3.4,
          "Max": 5.3,
          "Avg": 4.486,
          "Pct95": 5.2299999999999995
        },
        {
          "Kind": "etcd",
          "Resource": "cpu_usage_percent_cpu",
          "Min": 6.9,
          "Max": 9.9,
          "Avg": 8.251999999999999,
          "Pct95": 9.815999999999999
        },
        {
          "Kind": "dockerd-current_",
          "Resource": "cpu_usage_percent_cpu",
          "Min": 1,
          "Max": 1.5,
          "Avg": 1.2466666666666668,
          "Pct95": 1.5
        },
        {
          "Kind": "prometheus_",
          "Resource": "cpu_usage_percent_cpu",
          "Min": 61,
          "Max": 400.9,
          "Avg": 105.86466666666665,
          "Pct95": 192.78999999999968
        },
        {
          "Kind": "systemd_--switched-root",
          "Resource": "cpu_usage_percent_cpu",
          "Min": 0,
          "Max": 0.1,
          "Avg": 0.020000000000000004,
          "Pct95": 0.1
        },
        {
          "Kind": "openshift_start_network_",
          "Resource": "cpu_usage_percent_cpu",
          "Min": 0.1,
          "Max": 1,
          "Avg": 0.5066666666666666,
          "Pct95": 0.9299999999999999
        },
        {
          "Kind": "ovs-vswitchd_unix",
          "Resource": "cpu_usage_percent_cpu",
          "Min": 0.1,
          "Max": 0.3,
          "Avg": 0.17333333333333337,
          "Pct95": 0.22999999999999987
        },
        {
          "Kind": "fluentd",
          "Resource": "cpu_usage_percent_cpu",
          "Min": 0,
          "Max": 0.2,
          "Avg": 0.020000000000000004,
          "Pct95": 0.1299999999999999
        },
        {
          "Kind": "vda-write",
          "Resource": "disk_IOPS",
          "Min": 2.7,
          "Max": 46.6,
          "Avg": 9.600000000000001,
          "Pct95": 25.52999999999997
        },
        {
          "Kind": "vda-read",
          "Resource": "disk_IOPS",
          "Min": 0,
          "Max": 0,
          "Avg": 0,
          "Pct95": 0
        },
        {
          "Kind": "nvme0n1-write",
          "Resource": "disk_IOPS",
          "Min": 273.2,
          "Max": 350,
          "Avg": 336.5,
          "Pct95": 348.25
        },
        {
          "Kind": "nvme0n1-read",
          "Resource": "disk_IOPS",
          "Min": 0,
          "Max": 0,
          "Avg": 0,
          "Pct95": 0
        },
        {
          "Kind": "openshift_start_master_api_",
          "Resource": "memory_usage_resident_set_size",
          "Min": 1427084,
          "Max": 1437748,
          "Avg": 1432761.6,
          "Pct95": 1437748
        },
        {
          "Kind": "openshift_start_master_controllers_",
          "Resource": "memory_usage_resident_set_size",
          "Min": 320392,
          "Max": 320392,
          "Avg": 320392,
          "Pct95": 320392
        },
        {
          "Kind": "hyperkube_kubelet_",
          "Resource": "memory_usage_resident_set_size",
          "Min": 127416,
          "Max": 127676,
          "Avg": 127597.6,
          "Pct95": 127673.20000000001
        },
        {
          "Kind": "etcd",
          "Resource": "memory_usage_resident_set_size",
          "Min": 2371360,
          "Max": 2484020,
          "Avg": 2421219.7333333334,
          "Pct95": 2470529.6
        },
        {
          "Kind": "dockerd-current_",
          "Resource": "memory_usage_resident_set_size",
          "Min": 60440,
          "Max": 60440,
          "Avg": 60440,
          "Pct95": 60440
        },
        {
          "Kind": "prometheus_",
          "Resource": "memory_usage_resident_set_size",
          "Min": 18406024,
          "Max": 18650640,
          "Avg": 18446743.466666665,
          "Pct95": 18568661.6
        },
        {
          "Kind": "systemd_--switched-root",
          "Resource": "memory_usage_resident_set_size",
          "Min": 7972,
          "Max": 7972,
          "Avg": 7972,
          "Pct95": 7972
        },
        {
          "Kind": "openshift_start_network_",
          "Resource": "memory_usage_resident_set_size",
          "Min": 129512,
          "Max": 133272,
          "Avg": 130013.33333333333,
          "Pct95": 133272
        },
        {
          "Kind": "ovs-vswitchd_unix",
          "Resource": "memory_usage_resident_set_size",
          "Min": 145816,
          "Max": 145816,
          "Avg": 145816,
          "Pct95": 145816
        },
        {
          "Kind": "fluentd",
          "Resource": "memory_usage_resident_set_size",
          "Min": 56752,
          "Max": 56752,
          "Avg": 56752,
          "Pct95": 56752
        },
        {
          "Kind": "eth0-rx",
          "Resource": "network_l2_network_Mbits_sec",
          "Min": 33.4626816,
          "Max": 514.40902144,
          "Avg": 69.77835827199998,
          "Pct95": 209.46412339199952
        },
        {
          "Kind": "eth0-tx",
          "Resource": "network_l2_network_Mbits_sec",
          "Min": 7.33134848,
          "Max": 306.55250432,
          "Avg": 33.47008716799999,
          "Pct95": 124.98912870399974
        },
        {
          "Kind": "eth0-rx",
          "Resource": "network_l2_network_packets_sec",
          "Min": 1822.6,
          "Max": 29677.7,
          "Avg": 3883.142,
          "Pct95": 10680.539999999972
        },
        {
          "Kind": "eth0-tx",
          "Resource": "network_l2_network_packets_sec",
          "Min": 1708.6,
          "Max": 13916.4,
          "Avg": 2763.174,
          "Pct95": 5839.309999999987
        }
      ]
    },
    {
      "Kind": "svt_master_2_etcd_2",
      "Results": [
        {
          "Kind": "openshift_start_master_api_",
          "Resource": "cpu_usage_percent_cpu",
          "Min": 28.2,
          "Max": 72.93,
          "Avg": 41.44199999999999,
          "Pct95": 62.968999999999994
        },
        {
          "Kind": "openshift_start_master_controllers_",
          "Resource": "cpu_usage_percent_cpu",
          "Min": 10.3,
          "Max": 231.7,
          "Avg": 33.75933333333334,
          "Pct95": 127.32999999999984
        },
        {
          "Kind": "hyperkube_kubelet_",
          "Resource": "cpu_usage_percent_cpu",
          "Min": 2.9,
          "Max": 4.8,
          "Avg": 4.14,
          "Pct95": 4.59
        },
        {
          "Kind": "etcd",
          "Resource": "cpu_usage_percent_cpu",
          "Min": 19.6,
          "Max": 25.4,
          "Avg": 22.90533333333333,
          "Pct95": 25.33
        },
        {
          "Kind": "dockerd-current_",
          "Resource": "cpu_usage_percent_cpu",
          "Min": 1.1,
          "Max": 1.5,
          "Avg": 1.2866666666666666,
          "Pct95": 1.4299999999999997
        },
        {
          "Kind": "systemd_--switched-root",
          "Resource": "cpu_usage_percent_cpu",
          "Min": 0,
          "Max": 0.1,
          "Avg": 0.013333333333333334,
          "Pct95": 0.1
        },
        {
          "Kind": "openshift_start_network_",
          "Resource": "cpu_usage_percent_cpu",
          "Min": 0.1,
          "Max": 1.1,
          "Avg": 0.5133333333333334,
          "Pct95": 1.1
        },
        {
          "Kind": "ovs-vswitchd_unix",
          "Resource": "cpu_usage_percent_cpu",
          "Min": 0.1,
          "Max": 0.3,
          "Avg": 0.18000000000000005,
          "Pct95": 0.3
        },
        {
          "Kind": "vda-write",
          "Resource": "disk_IOPS",
          "Min": 0,
          "Max": 45,
          "Avg": 5.993333333333334,
          "Pct95": 25.959999999999972
        },
        {
          "Kind": "vda-read",
          "Resource": "disk_IOPS",
          "Min": 0,
          "Max": 0,
          "Avg": 0,
          "Pct95": 0
        },
        {
          "Kind": "nvme0n1-write",
          "Resource": "disk_IOPS",
          "Min": 310.9,
          "Max": 346,
          "Avg": 335.97333333333336,
          "Pct95": 345.86
        },
        {
          "Kind": "nvme0n1-read",
          "Resource": "disk_IOPS",
          "Min": 0,
          "Max": 0,
          "Avg": 0,
          "Pct95": 0
        },
        {
          "Kind": "openshift_start_master_api_",
          "Resource": "memory_usage_resident_set_size",
          "Min": 2315188,
          "Max": 2345324,
          "Avg": 2324682.4,
          "Pct95": 2345324
        },
        {
          "Kind": "openshift_start_master_controllers_",
          "Resource": "memory_usage_resident_set_size",
          "Min": 3762932,
          "Max": 3827716,
          "Avg": 3784526.6666666665,
          "Pct95": 3827716
        },
        {
          "Kind": "hyperkube_kubelet_",
          "Resource": "memory_usage_resident_set_size",
          "Min": 133232,
          "Max": 133308,
          "Avg": 133254.66666666666,
          "Pct95": 133308
        },
        {
          "Kind": "etcd",
          "Resource": "memory_usage_resident_set_size",
          "Min": 2514584,
          "Max": 2576428,
          "Avg": 2543815.7333333334,
          "Pct95": 2576428
        },
        {
          "Kind": "dockerd-current_",
          "Resource": "memory_usage_resident_set_size",
          "Min": 72320,
          "Max": 72320,
          "Avg": 72320,
          "Pct95": 72320
        },
        {
          "Kind": "systemd_--switched-root",
          "Resource": "memory_usage_resident_set_size",
          "Min": 7920,
          "Max": 7920,
          "Avg": 7920,
          "Pct95": 7920
        },
        {
          "Kind": "openshift_start_network_",
          "Resource": "memory_usage_resident_set_size",
          "Min": 143724,
          "Max": 152756,
          "Avg": 146734.66666666666,
          "Pct95": 152756
        },
        {
          "Kind": "ovs-vswitchd_unix",
          "Resource": "memory_usage_resident_set_size",
          "Min": 145628,
          "Max": 145628,
          "Avg": 145628,
          "Pct95": 145628
        },
        {
          "Kind": "eth0-rx",
          "Resource": "network_l2_network_Mbits_sec",
          "Min": 16.12488704,
          "Max": 338.92974592,
          "Avg": 39.58857728,
          "Pct95": 128.28355788799968
        },
        {
          "Kind": "eth0-tx",
          "Resource": "network_l2_network_Mbits_sec",
          "Min": 35.75119872,
          "Max": 193.99958528,
          "Avg": 50.75913932799999,
          "Pct95": 114.96183398399987
        },
        {
          "Kind": "eth0-rx",
          "Resource": "network_l2_network_packets_sec",
          "Min": 3117.3,
          "Max": 32883.6,
          "Avg": 5303.61,
          "Pct95": 12431.20999999997
        },
        {
          "Kind": "eth0-tx",
          "Resource": "network_l2_network_packets_sec",
          "Min": 3103.4,
          "Max": 13764.4,
          "Avg": 4022.9259999999995,
          "Pct95": 6700.839999999989
        }
      ]
    },
    {
      "Kind": "svt_master_3_etcd_3",
      "Results": [
        {
          "Kind": "openshift_start_master_api_",
          "Resource": "cpu_usage_percent_cpu",
          "Min": 23.1,
          "Max": 59,
          "Avg": 33.675333333333334,
          "Pct95": 49.19999999999999
        },
        {
          "Kind": "openshift_start_master_controllers_",
          "Resource": "cpu_usage_percent_cpu",
          "Min": 1.8,
          "Max": 5.5,
          "Avg": 2.426666666666667,
          "Pct95": 5.219999999999999
        },
        {
          "Kind": "hyperkube_kubelet_",
          "Resource": "cpu_usage_percent_cpu",
          "Min": 3.2,
          "Max": 7.09,
          "Avg": 5.112666666666666,
          "Pct95": 6.817
        },
        {
          "Kind": "etcd",
          "Resource": "cpu_usage_percent_cpu",
          "Min": 14.8,
          "Max": 19.2,
          "Avg": 16.931333333333335,
          "Pct95": 19.06
        },
        {
          "Kind": "dockerd-current_",
          "Resource": "cpu_usage_percent_cpu",
          "Min": 1.2,
          "Max": 2.1,
          "Avg": 1.5199999999999998,
          "Pct95": 1.96
        },
        {
          "Kind": "systemd_--switched-root",
          "Resource": "cpu_usage_percent_cpu",
          "Min": 0,
          "Max": 0.2,
          "Avg": 0.03333333333333333,
          "Pct95": 0.1299999999999999
        },
        {
          "Kind": "openshift_start_network_",
          "Resource": "cpu_usage_percent_cpu",
          "Min": 0,
          "Max": 1.1,
          "Avg": 0.5400000000000001,
          "Pct95": 1.0299999999999998
        },
        {
          "Kind": "ovs-vswitchd_unix",
          "Resource": "cpu_usage_percent_cpu",
          "Min": 0,
          "Max": 0.4,
          "Avg": 0.20666666666666667,
          "Pct95": 0.4
        },
        {
          "Kind": "vda-write",
          "Resource": "disk_IOPS",
          "Min": 0.2,
          "Max": 63.7,
          "Avg": 11.120000000000001,
          "Pct95": 31.77999999999995
        },
        {
          "Kind": "vda-read",
          "Resource": "disk_IOPS",
          "Min": 45.3,
          "Max": 65.4,
          "Avg": 55.919999999999995,
          "Pct95": 64.35
        },
        {
          "Kind": "nvme0n1-write",
          "Resource": "disk_IOPS",
          "Min": 303.1,
          "Max": 341.8,
          "Avg": 329.93999999999994,
          "Pct95": 340.12
        },
        {
          "Kind": "nvme0n1-read",
          "Resource": "disk_IOPS",
          "Min": 0,
          "Max": 0,
          "Avg": 0,
          "Pct95": 0
        },
        {
          "Kind": "openshift_start_master_api_",
          "Resource": "memory_usage_resident_set_size",
          "Min": 2114388,
          "Max": 2143152,
          "Avg": 2136593.6,
          "Pct95": 2143152
        },
        {
          "Kind": "openshift_start_master_controllers_",
          "Resource": "memory_usage_resident_set_size",
          "Min": 461428,
          "Max": 462252,
          "Avg": 461812.5333333333,
          "Pct95": 462252
        },
        {
          "Kind": "hyperkube_kubelet_",
          "Resource": "memory_usage_resident_set_size",
          "Min": 141168,
          "Max": 141168,
          "Avg": 141168,
          "Pct95": 141168
        },
        {
          "Kind": "etcd",
          "Resource": "memory_usage_resident_set_size",
          "Min": 2640428,
          "Max": 2779540,
          "Avg": 2710646.6666666665,
          "Pct95": 2779540
        },
        {
          "Kind": "dockerd-current_",
          "Resource": "memory_usage_resident_set_size",
          "Min": 79124,
          "Max": 79124,
          "Avg": 79124,
          "Pct95": 79124
        },
        {
          "Kind": "systemd_--switched-root",
          "Resource": "memory_usage_resident_set_size",
          "Min": 8008,
          "Max": 8008,
          "Avg": 8008,
          "Pct95": 8008
        },
        {
          "Kind": "openshift_start_network_",
          "Resource": "memory_usage_resident_set_size",
          "Min": 143300,
          "Max": 151788,
          "Avg": 146695.2,
          "Pct95": 151788
        },
        {
          "Kind": "ovs-vswitchd_unix",
          "Resource": "memory_usage_resident_set_size",
          "Min": 145636,
          "Max": 145636,
          "Avg": 145636,
          "Pct95": 145636
        },
        {
          "Kind": "eth0-rx",
          "Resource": "network_l2_network_Mbits_sec",
          "Min": 19.53316864,
          "Max": 168.28071936,
          "Avg": 33.795424256000004,
          "Pct95": 78.03187199999986
        },
        {
          "Kind": "eth0-tx",
          "Resource": "network_l2_network_Mbits_sec",
          "Min": 23.32737536,
          "Max": 31.3106432,
          "Avg": 24.807691605333332,
          "Pct95": 27.385102335999996
        },
        {
          "Kind": "eth0-rx",
          "Resource": "network_l2_network_packets_sec",
          "Min": 3266.9,
          "Max": 7291.2,
          "Avg": 3790.12,
          "Pct95": 4860.099999999997
        },
        {
          "Kind": "eth0-tx",
          "Resource": "network_l2_network_packets_sec",
          "Min": 3213.1,
          "Max": 6852.6,
          "Avg": 3708.6000000000004,
          "Pct95": 4683.159999999997
        }
      ]
    },
    {
      "Kind": "svt_node_1",
      "Results": [
        {
          "Kind": "hyperkube_kubelet_",
          "Resource": "cpu_usage_percent_cpu",
          "Min": 2.1,
          "Max": 3.3,
          "Avg": 2.786666666666667,
          "Pct95": 3.2299999999999995
        },
        {
          "Kind": "dockerd-current_",
          "Resource": "cpu_usage_percent_cpu",
          "Min": 0.5,
          "Max": 0.8,
          "Avg": 0.7,
          "Pct95": 0.8
        },
        {
          "Kind": "systemd_--switched-root",
          "Resource": "cpu_usage_percent_cpu",
          "Min": 0,
          "Max": 0.1,
          "Avg": 0.013333333333333334,
          "Pct95": 0.1
        },
        {
          "Kind": "openshift_start_network_",
          "Resource": "cpu_usage_percent_cpu",
          "Min": 0.1,
          "Max": 1.1,
          "Avg": 0.48000000000000004,
          "Pct95": 0.8899999999999997
        },
        {
          "Kind": "ovs-vswitchd_unix",
          "Resource": "cpu_usage_percent_cpu",
          "Min": 0,
          "Max": 0.2,
          "Avg": 0.07333333333333333,
          "Pct95": 0.2
        },
        {
          "Kind": "vda-write",
          "Resource": "disk_IOPS",
          "Min": 0,
          "Max": 4.5,
          "Avg": 1.24,
          "Pct95": 3.939999999999999
        },
        {
          "Kind": "vda-read",
          "Resource": "disk_IOPS",
          "Min": 0,
          "Max": 0.1,
          "Avg": 0.006666666666666667,
          "Pct95": 0.029999999999999895
        },
        {
          "Kind": "hyperkube_kubelet_",
          "Resource": "memory_usage_resident_set_size",
          "Min": 119728,
          "Max": 120428,
          "Avg": 120113.86666666667,
          "Pct95": 120234.79999999999
        },
        {
          "Kind": "dockerd-current_",
          "Resource": "memory_usage_resident_set_size",
          "Min": 62140,
          "Max": 62140,
          "Avg": 62140,
          "Pct95": 62140
        },
        {
          "Kind": "systemd_--switched-root",
          "Resource": "memory_usage_resident_set_size",
          "Min": 7656,
          "Max": 7656,
          "Avg": 7656,
          "Pct95": 7656
        },
        {
          "Kind": "openshift_start_network_",
          "Resource": "memory_usage_resident_set_size",
          "Min": 134448,
          "Max": 145016,
          "Avg": 141316.8,
          "Pct95": 145016
        },
        {
          "Kind": "ovs-vswitchd_unix",
          "Resource": "memory_usage_resident_set_size",
          "Min": 48800,
          "Max": 48800,
          "Avg": 48800,
          "Pct95": 48800
        },
        {
          "Kind": "eth0-rx",
          "Resource": "network_l2_network_Mbits_sec",
          "Min": 0.02080768,
          "Max": 0.04554752,
          "Avg": 0.03224371200000001,
          "Pct95": 0.044687359999999995
        },
        {
          "Kind": "eth0-tx",
          "Resource": "network_l2_network_Mbits_sec",
          "Min": 0.01581056,
          "Max": 0.06774784,
          "Avg": 0.047218687999999995,
          "Pct95": 0.06746111999999999
        },
        {
          "Kind": "eth0-rx",
          "Resource": "network_l2_network_packets_sec",
          "Min": 3.4,
          "Max": 8.4,
          "Avg": 5.753333333333332,
          "Pct95": 7.77
        },
        {
          "Kind": "eth0-tx",
          "Resource": "network_l2_network_packets_sec",
          "Min": 2.7,
          "Max": 7.5,
          "Avg": 4.7733333333333325,
          "Pct95": 6.659999999999998
        }
      ]
    },
    {
      "Kind": "svt_node_2",
      "Results": [
        {
          "Kind": "hyperkube_kubelet_",
          "Resource": "cpu_usage_percent_cpu",
          "Min": 2,
          "Max": 3.6,
          "Avg": 2.973333333333333,
          "Pct95": 3.5300000000000002
        },
        {
          "Kind": "dockerd-current_",
          "Resource": "cpu_usage_percent_cpu",
          "Min": 0.4,
          "Max": 0.9,
          "Avg": 0.5999999999999999,
          "Pct95": 0.8299999999999998
        },
        {
          "Kind": "systemd_--switched-root",
          "Resource": "cpu_usage_percent_cpu",
          "Min": 0,
          "Max": 0.1,
          "Avg": 0.020000000000000004,
          "Pct95": 0.1
        },
        {
          "Kind": "openshift_start_network_",
          "Resource": "cpu_usage_percent_cpu",
          "Min": 0.2,
          "Max": 1.3,
          "Avg": 0.5066666666666667,
          "Pct95": 1.0899999999999996
        },
        {
          "Kind": "ovs-vswitchd_unix",
          "Resource": "cpu_usage_percent_cpu",
          "Min": 0,
          "Max": 0.2,
          "Avg": 0.08,
          "Pct95": 0.2
        },
        {
          "Kind": "vda-write",
          "Resource": "disk_IOPS",
          "Min": 0,
          "Max": 12.6,
          "Avg": 1.8666666666666663,
          "Pct95": 6.22999999999999
        },
        {
          "Kind": "vda-read",
          "Resource": "disk_IOPS",
          "Min": 0,
          "Max": 0,
          "Avg": 0,
          "Pct95": 0
        },
        {
          "Kind": "hyperkube_kubelet_",
          "Resource": "memory_usage_resident_set_size",
          "Min": 115552,
          "Max": 115680,
          "Avg": 115619.2,
          "Pct95": 115680
        },
        {
          "Kind": "dockerd-current_",
          "Resource": "memory_usage_resident_set_size",
          "Min": 54620,
          "Max": 54620,
          "Avg": 54620,
          "Pct95": 54620
        },
        {
          "Kind": "systemd_--switched-root",
          "Resource": "memory_usage_resident_set_size",
          "Min": 7572,
          "Max": 7572,
          "Avg": 7572,
          "Pct95": 7572
        },
        {
          "Kind": "openshift_start_network_",
          "Resource": "memory_usage_resident_set_size",
          "Min": 134192,
          "Max": 144744,
          "Avg": 141156.8,
          "Pct95": 144744
        },
        {
          "Kind": "ovs-vswitchd_unix",
          "Resource": "memory_usage_resident_set_size",
          "Min": 48668,
          "Max": 48668,
          "Avg": 48668,
          "Pct95": 48668
        },
        {
          "Kind": "eth0-rx",
          "Resource": "network_l2_network_Mbits_sec",
          "Min": 0.02187264,
          "Max": 0.06365184,
          "Avg": 0.031145984,
          "Pct95": 0.04988927999999998
        },
        {
          "Kind": "eth0-tx",
          "Resource": "network_l2_network_Mbits_sec",
          "Min": 0.0294912,
          "Max": 0.06545408,
          "Avg": 0.04643771733333334,
          "Pct95": 0.06476595199999999
        },
        {
          "Kind": "eth0-rx",
          "Resource": "network_l2_network_packets_sec",
          "Min": 4.3,
          "Max": 10.2,
          "Avg": 6.086666666666668,
          "Pct95": 8.099999999999998
        },
        {
          "Kind": "eth0-tx",
          "Resource": "network_l2_network_packets_sec",
          "Min": 3.6,
          "Max": 8.8,
          "Avg": 4.886666666666667,
          "Pct95": 6.629999999999997
        }
      ]
    }
  ],
  "Metrics": [
    {
      "marker": "cluster_loader_marker",
      "name": "cluster-loader-test",
      "type": "metrics.TestDuration",
      "startTime": "2018-05-08T13:52:16.310168376-04:00",
      "testDuration": "2m27.307403833s"
    }
  ]
}
